iqr_license_sdk/__init__.py
iqr_license_sdk/core.py
iqr_license_sdk/exceptions.py
iqr_license_sdk-0.1.1.dist-info/licenses/LICENSE
iqr_license_sdk-0.1.1.dist-info/METADATA
iqr_license_sdk-0.1.1.dist-info/WHEEL
iqr_license_sdk-0.1.1.dist-info/top_level.txt
iqr_license_sdk-0.1.1.dist-info/RECORD
