Metadata-Version: 2.4
Name: iqr_license_sdk
Version: 0.1.1
Summary: 一个用于软件授权的SDK工具包
Home-page: https://github.com/yourusername/iqr_license_sdk
Author: Mr_Yao
Author-email: 2316718372@qq.com
Classifier: Programming Language :: Python :: 3
Classifier: License :: OSI Approved :: MIT License
Classifier: Operating System :: OS Independent
Requires-Python: >=3.6
License-File: LICENSE
Requires-Dist: requests>=2.25.1
Requires-Dist: cryptography>=3.4.7
Dynamic: author
Dynamic: author-email
Dynamic: classifier
Dynamic: description
Dynamic: description-content-type
Dynamic: home-page
Dynamic: license-file
Dynamic: requires-dist
Dynamic: requires-python
Dynamic: summary
